AUTHORS
LICENSE
MANIFEST.in
README.rst
setup.py
datasource/__init__.py
datasource/api.py
datasource/exceptions.py
datasource/interface.py
datasource.egg-info/PKG-INFO
datasource.egg-info/SOURCES.txt
datasource.egg-info/dependency_links.txt
datasource.egg-info/requires.txt
datasource.egg-info/top_level.txt
datasource/impl/__init__.py
datasource/impl/file.py
datasource/impl/iterable.py
datasource/impl/remote.py
datasource/impl/string.py
datasource/utils/__init__.py
datasource/utils/helpers.py
datasource/utils/tempfile.py