Metadata-Version: 1.1
Name: datasource
Version: 0.1.0
Summary: DataSource is a simple wrapper for fetching data with a uniform API regardless how the data should be fetched.
Home-page: https://bitbucket.org/YAmikep/datasource
Author: Michael Palumbo
Author-email: michael.palumbo87@gmail.com
License: Copyright (C) 2013, Michael Palumbo
